supt_dashboard/__init__.py
supt_dashboard/dashboard.py
supt_dashboard-1.0.0.dist-info/licenses/LICENSE
supt_dashboard-1.0.0.dist-info/METADATA
supt_dashboard-1.0.0.dist-info/WHEEL
supt_dashboard-1.0.0.dist-info/top_level.txt
supt_dashboard-1.0.0.dist-info/RECORD
