Metadata-Version: 2.4
Name: supt-dashboard
Version: 1.0.0
Summary: SUPT ψ-Fold Dashboard with NOAA + USGS integration
Home-page: https://github.com/SunWolf77/supt-dashboard
Author: SunWolf77
License: MIT
Classifier: Programming Language :: Python :: 3
Classifier: License :: OSI Approved :: MIT License
Classifier: Operating System :: OS Independent
Requires-Python: >=3.9
License-File: LICENSE
Requires-Dist: requests
Requires-Dist: plotly
Dynamic: license-file
